AUTHORS.rst
CONTRIBUTING.rst
HISTORY.rst
LICENSE
MANIFEST.in
README.md
pyproject.toml
setup.cfg
src/trianglechain/BaseChain.py
src/trianglechain/LineChain.py
src/trianglechain/RectangleChain.py
src/trianglechain/TriangleChain.py
src/trianglechain/__init__.py
src/trianglechain/bestfit.py
src/trianglechain/density_estimation.py
src/trianglechain/limits.py
src/trianglechain/make_subplots.py
src/trianglechain/params.py
src/trianglechain/utils_pj_hpd.py
src/trianglechain/utils_plots.py
src/trianglechain.egg-info/PKG-INFO
src/trianglechain.egg-info/SOURCES.txt
src/trianglechain.egg-info/dependency_links.txt
src/trianglechain.egg-info/not-zip-safe
src/trianglechain.egg-info/requires.txt
src/trianglechain.egg-info/top_level.txt
tests/test_bestfit.py
tests/test_limits.py
tests/test_linechain.py
tests/test_params.py
tests/test_rectanglechain.py
tests/test_trianglechain.py
tests/test_utils.py