Metadata-Version: 2.1
Name: trianglechain
Version: 0.6.0
Summary: Code to plot multidimensional distributions
Author: Silvan Fischbacher, Tomasz Kacprzak
Author-email: silvanf@phys.ethz.ch, tomaszk@phys.ethz.ch
License: MIT License
Project-URL: Source, https://cosmo-docs.phys.ethz.ch/trianglechain
Classifier: Intended Audience :: Science/Research
Classifier: Intended Audience :: Developers
Classifier: License :: OSI Approved :: MIT License
Classifier: Natural Language :: English
Classifier: Programming Language :: Python :: 3
Classifier: Programming Language :: Python :: 3.9
Classifier: Programming Language :: Python :: 3.10
Classifier: Operating System :: OS Independent
Requires-Python: >=3.7
Provides-Extra: dev
Provides-Extra: docs
License-File: LICENSE
License-File: AUTHORS.rst
